do_data_utils/__init__.py
do_data_utils/version.py
do_data_utils/azure/__init__.py
do_data_utils/azure/azureutils.py
do_data_utils/azure/keyvault.py
do_data_utils/azure/storage.py
do_data_utils/google/__init__.py
do_data_utils/google/common.py
do_data_utils/google/gbqutils.py
do_data_utils/google/gcputils.py
do_data_utils/google/google_secret.py
do_data_utils/pathutils/__init__.py
do_data_utils/preprocessing/__init__.py
do_data_utils/preprocessing/citizenid.py
do_data_utils/preprocessing/common.py
do_data_utils/preprocessing/constants.py
do_data_utils/preprocessing/email.py
do_data_utils/preprocessing/phone.py
do_data_utils/sharepoint/__init__.py
do_data_utils/sharepoint/shputils.py
do_data_utils-4.2.1.dist-info/METADATA
do_data_utils-4.2.1.dist-info/WHEEL
do_data_utils-4.2.1.dist-info/licenses/LICENSE
do_data_utils-4.2.1.dist-info/RECORD
