Metadata-Version: 2.4
Name: do-data-utils
Version: 4.2.1
Summary: Functionalities to interact with Google and Azure, and clean data
Project-URL: Repository, https://github.com/anuponwa/do-data-utils
Author-email: Anupong Wannakrairot <anuponwa@scg.com>
License: MIT License
License-File: LICENSE
Classifier: Development Status :: 4 - Beta
Classifier: Intended Audience :: Developers
Classifier: Intended Audience :: Information Technology
Classifier: Intended Audience :: Science/Research
Classifier: License :: OSI Approved :: MIT License
Classifier: Operating System :: OS Independent
Classifier: Programming Language :: Python
Classifier: Programming Language :: Python :: 3
Classifier: Programming Language :: Python :: 3.12
Classifier: Topic :: Database :: Database Engines/Servers
Classifier: Topic :: Scientific/Engineering :: Information Analysis
Classifier: Topic :: Software Development :: Libraries :: Python Modules
Requires-Python: >=3.9
Requires-Dist: azure-identity~=1.19.0
Requires-Dist: azure-keyvault~=4.2.0
Requires-Dist: azure-storage-file-datalake~=12.18.0
Requires-Dist: databricks-sdk~=0.36.0
Requires-Dist: databricks-sql-connector~=3.6.0
Requires-Dist: db-dtypes~=1.4.1
Requires-Dist: google-api-core~=2.21.0
Requires-Dist: google-auth~=2.35.0
Requires-Dist: google-cloud-bigquery~=3.26.0
Requires-Dist: google-cloud-core~=2.4.1
Requires-Dist: google-cloud-secret-manager~=2.21.0
Requires-Dist: google-cloud-storage~=2.18.2
Requires-Dist: google-cloud~=0.34.0
Requires-Dist: google-crc32c~=1.6.0
Requires-Dist: google~=3.0.0
Requires-Dist: msal~=1.31.1
Requires-Dist: openpyxl>=3.0.0
Requires-Dist: pandas>=2.0.0
Requires-Dist: polars>=0.18.0
Requires-Dist: xlsxwriter>=3.0.0
